phrasetms_client/__init__.py
phrasetms_client/api_client.py
phrasetms_client/api_response.py
phrasetms_client/configuration.py
phrasetms_client/exceptions.py
phrasetms_client/rest.py
phrasetms_client/utils.py
phrasetms_client/api/__init__.py
phrasetms_client/api/additional_workflow_step_api.py
phrasetms_client/api/analysis_api.py
phrasetms_client/api/async_request_api.py
phrasetms_client/api/authentication_api.py
phrasetms_client/api/bilingual_file_api.py
phrasetms_client/api/business_unit_api.py
phrasetms_client/api/client_api.py
phrasetms_client/api/connector_api.py
phrasetms_client/api/conversations_api.py
phrasetms_client/api/cost_center_api.py
phrasetms_client/api/custom_fields_api.py
phrasetms_client/api/custom_file_type_api.py
phrasetms_client/api/domain_api.py
phrasetms_client/api/email_template_api.py
phrasetms_client/api/file_api.py
phrasetms_client/api/glossary_api.py
phrasetms_client/api/import_settings_api.py
phrasetms_client/api/job_api.py
phrasetms_client/api/language_quality_assessment_api.py
phrasetms_client/api/machine_translation_api.py
phrasetms_client/api/machine_translation_settings_api.py
phrasetms_client/api/mapping_api.py
phrasetms_client/api/net_rate_scheme_api.py
phrasetms_client/api/price_list_api.py
phrasetms_client/api/project_api.py
phrasetms_client/api/project_reference_file_api.py
phrasetms_client/api/project_template_api.py
phrasetms_client/api/provider_api.py
phrasetms_client/api/quality_assurance_api.py
phrasetms_client/api/quote_api.py
phrasetms_client/api/scim_api.py
phrasetms_client/api/segment_api.py
phrasetms_client/api/segmentation_rules_api.py
phrasetms_client/api/spell_check_api.py
phrasetms_client/api/sub_domain_api.py
phrasetms_client/api/supported_languages_api.py
phrasetms_client/api/term_base_api.py
phrasetms_client/api/translation_api.py
phrasetms_client/api/translation_memory_api.py
phrasetms_client/api/user_api.py
phrasetms_client/api/vendor_api.py
phrasetms_client/api/webhook_api.py
phrasetms_client-0.3.14.dist-info/licenses/LICENSE.md
phrasetms_client-0.3.14.dist-info/METADATA
phrasetms_client-0.3.14.dist-info/WHEEL
phrasetms_client-0.3.14.dist-info/top_level.txt
phrasetms_client-0.3.14.dist-info/RECORD
