Metadata-Version: 2.4
Name: phrasetms-client
Version: 0.3.14
Summary: Phrase TMS API
Home-page: https://github.com/Martin005/phrasetms-python
Author: Martin Chrástek
Author-email: 
License: LGPL-3.0
Keywords: OpenAPI,OpenAPI-Generator,Phrase TMS API
License-File: LICENSE.md
Requires-Dist: urllib3>=1.25.3
Requires-Dist: python-dateutil
Requires-Dist: pydantic<2,>=1.10.5
Requires-Dist: aenum
Dynamic: author
Dynamic: description
Dynamic: description-content-type
Dynamic: home-page
Dynamic: keywords
Dynamic: license
Dynamic: license-file
Dynamic: requires-dist
Dynamic: summary
